{
  "main": {
    "id": "d8655e36c9c2be55",
    "type": "split",
    "children": [
      {
        "id": "1fc3a69493ec04fb",
        "type": "tabs",
        "children": [
          {
            "id": "b0dc8dfc767db7cc",
            "type": "leaf",
            "state": {
              "type": "markdown",
              "state": {
                "file": "Loren Soth.md",
                "mode": "source",
                "source": false
              },
              "icon": "lucide-file",
              "title": "Loren Soth"
            }
          },
          {
            "id": "b8a789ad7a644b02",
            "type": "leaf",
            "state": {
              "type": "graph",
              "state": {},
              "icon": "lucide-git-fork",
              "title": "Graph view"
            }
          },
          {
            "id": "8834784b4eb06c68",
            "type": "leaf",
            "state": {
              "type": "markdown",
              "state": {
                "file": "Knights of Solamnia.md",
                "mode": "source",
                "source": false
              },
              "icon": "lucide-file",
              "title": "Knights of Solamnia"
            }
          },
          {
            "id": "ea02bba90fa26696",
            "type": "leaf",
            "state": {
              "type": "markdown",
              "state": {
                "file": "The Cataclysm.md",
                "mode": "source",
                "source": false
              },
              "icon": "lucide-file",
              "title": "The Cataclysm"
            }
          }
        ],
        "currentTab": 1
      }
    ],
    "direction": "vertical"
  },
  "left": {
    "id": "4b81672face1609f",
    "type": "split",
    "children": [
      {
        "id": "bbf21f20e2e45156",
        "type": "tabs",
        "children": [
          {
            "id": "24e049151717a72c",
            "type": "leaf",
            "state": {
              "type": "file-explorer",
              "state": {
                "sortOrder": "alphabetical"
              },
              "icon": "lucide-folder-closed",
              "title": "Files"
            }
          },
          {
            "id": "b1f9ac94a2b5ba97",
            "type": "leaf",
            "state": {
              "type": "search",
              "state": {
                "query": "",
                "matchingCase": false,
                "explainSearch": false,
                "collapseAll": false,
                "extraContext": false,
                "sortOrder": "alphabetical"
              },
              "icon": "lucide-search",
              "title": "Search"
            }
          },
          {
            "id": "7975d91d9c94256e",
            "type": "leaf",
            "state": {
              "type": "bookmarks",
              "state": {},
              "icon": "lucide-bookmark",
              "title": "Bookmarks"
            }
          }
        ]
      }
    ],
    "direction": "horizontal",
    "width": 300
  },
  "right": {
    "id": "1ea301fa6e299214",
    "type": "split",
    "children": [
      {
        "id": "7128a7ea7c6755c4",
        "type": "tabs",
        "children": [
          {
            "id": "679c2de747aeed04",
            "type": "leaf",
            "state": {
              "type": "backlink",
              "state": {
                "file": "Loren Soth.md",
                "collapseAll": false,
                "extraContext": false,
                "sortOrder": "alphabetical",
                "showSearch": false,
                "searchQuery": "",
                "backlinkCollapsed": false,
                "unlinkedCollapsed": true
              },
              "icon": "links-coming-in",
              "title": "Backlinks for Loren Soth"
            }
          },
          {
            "id": "409961aeef776dd0",
            "type": "leaf",
            "state": {
              "type": "outgoing-link",
              "state": {
                "file": "Loren Soth.md",
                "linksCollapsed": false,
                "unlinkedCollapsed": true
              },
              "icon": "links-going-out",
              "title": "Outgoing links from Loren Soth"
            }
          },
          {
            "id": "4d92012f99407d19",
            "type": "leaf",
            "state": {
              "type": "tag",
              "state": {
                "sortOrder": "frequency",
                "useHierarchy": true
              },
              "icon": "lucide-tags",
              "title": "Tags"
            }
          },
          {
            "id": "86f85c93a4f7109f",
            "type": "leaf",
            "state": {
              "type": "all-properties",
              "state": {
                "sortOrder": "frequency",
                "showSearch": false,
                "searchQuery": ""
              },
              "icon": "lucide-archive",
              "title": "All properties"
            }
          },
          {
            "id": "6ce9b45998827997",
            "type": "leaf",
            "state": {
              "type": "outline",
              "state": {
                "file": "Loren Soth.md"
              },
              "icon": "lucide-list",
              "title": "Outline of Loren Soth"
            }
          }
        ]
      }
    ],
    "direction": "horizontal",
    "width": 300,
    "collapsed": true
  },
  "left-ribbon": {
    "hiddenItems": {
      "switcher:Open quick switcher": false,
      "graph:Open graph view": false,
      "canvas:Create new canvas": false,
      "daily-notes:Open today's daily note": false,
      "templates:Insert template": false,
      "command-palette:Open command palette": false,
      "table-editor-obsidian:Advanced Tables Toolbar": false,
      "obsidian-leaflet-plugin:Open Leaflet Map": false,
      "obsidian42-brat:BRAT": false,
      "obsidian-gallery:Gallery": false
    }
  },
  "active": "b8a789ad7a644b02",
  "lastOpenFiles": [
    "Ketras Notebook.md",
    "Loren Soth.md",
    "The Cataclysm.md",
    "Huma Dragonbane.md",
    "Ketra.md",
    "Map.md",
    "Images/ansalon-poster-map.webp",
    "Knights of Solamnia.md",
    "Images/Knights of the Rose.png",
    "Images/Knights of the Sword.png",
    "Images/Knights of the Crown.png",
    "Images",
    "plugins/tag-wrangler/styles.css",
    "plugins/tag-wrangler/manifest.json",
    "plugins/tag-wrangler/main.js",
    "plugins/table-editor-obsidian/styles.css",
    "plugins/table-editor-obsidian/manifest.json",
    "plugins/table-editor-obsidian/main.js",
    "plugins/table-editor-obsidian/data.json",
    "plugins/obsidian-outliner/styles.css",
    "plugins/obsidian-outliner/manifest.json"
  ]
}